agent0/__init__.py
agent0/min-hyperdrive.version
agent0/chainsync/__init__.py
agent0/chainsync/df_to_db.py
agent0/chainsync/postgres_config.py
agent0/chainsync/analysis/__init__.py
agent0/chainsync/analysis/calc_position_value.py
agent0/chainsync/analysis/db_to_analysis.py
agent0/chainsync/dashboard/__init__.py
agent0/chainsync/dashboard/build_dashboard_dfs.py
agent0/chainsync/dashboard/build_fixed_rate.py
agent0/chainsync/dashboard/build_leaderboard.py
agent0/chainsync/dashboard/build_ohlcv.py
agent0/chainsync/dashboard/build_outstanding_positions.py
agent0/chainsync/dashboard/build_ticker.py
agent0/chainsync/dashboard/build_variable_rate.py
agent0/chainsync/dashboard/build_vault_share_price.py
agent0/chainsync/dashboard/build_wallet_positions.py
agent0/chainsync/dashboard/plot_ohlcv.py
agent0/chainsync/dashboard/plot_outstanding_positions.py
agent0/chainsync/dashboard/plot_rates.py
agent0/chainsync/dashboard/plot_share_price.py
agent0/chainsync/dashboard/plot_utils.py
agent0/chainsync/dashboard/usernames.py
agent0/chainsync/db/__init__.py
agent0/chainsync/db/base/__init__.py
agent0/chainsync/db/base/interface.py
agent0/chainsync/db/base/interface_test.py
agent0/chainsync/db/base/schema.py
agent0/chainsync/db/base/schema_test.py
agent0/chainsync/db/hyperdrive/__init__.py
agent0/chainsync/db/hyperdrive/chain_to_db.py
agent0/chainsync/db/hyperdrive/convert_data.py
agent0/chainsync/db/hyperdrive/event_getters.py
agent0/chainsync/db/hyperdrive/import_export_data.py
agent0/chainsync/db/hyperdrive/import_export_data_test.py
agent0/chainsync/db/hyperdrive/interface.py
agent0/chainsync/db/hyperdrive/interface_test.py
agent0/chainsync/db/hyperdrive/schema.py
agent0/chainsync/db/hyperdrive/schema_test.py
agent0/chainsync/exec/__init__.py
agent0/chainsync/exec/acquire_data.py
agent0/chainsync/exec/analyze_data.py
agent0/chainsync/streamlit/Dashboard.py
agent0/chainsync/streamlit/pages/Wallet_Stats.py
agent0/chainsync/test_fixtures/__init__.py
agent0-0.26.2.dist-info/WHEEL
agent0-0.26.2.dist-info/METADATA
agent0-0.26.2.dist-info/RECORD
