Metadata-Version: 2.3
Name: agent0
Version: 0.26.2
Summary: Agent interface for on-chain protocols.
Author-email: Dylan Paiton <dylan@delv.tech>, Mihai Cosma <mihai@delv.tech>, Matthew Brown <matt@delv.tech>, Sheng Lundquist <sheng@delv.tech>, Jonny Rhea <jonny@delv.tech>, Alex Towle <alex@delv.tech>, Giovanni Effio <mazygio@delv.tech>, Ryan Goree <ryan@delv.tech>
Requires-Python: >=3.10, <=3.11
Classifier: Programming Language :: Python :: 3
Classifier: License :: OSI Approved :: Apache Software License
Classifier: Operating System :: OS Independent
Classifier: Development Status :: 3 - Alpha
Classifier: Natural Language :: English
Requires-Dist: dill>=0.3.8
Requires-Dist: docker>=7.1.0
Requires-Dist: eth-abi>=5.1.0
Requires-Dist: eth-typing>=5.0.0
Requires-Dist: eth-account>=0.13.3
Requires-Dist: fixedpointmath>=0.2.1
Requires-Dist: hexbytes>=1.2.1
Requires-Dist: hyperdrivepy>=0.17.1
Requires-Dist: hyperdrivetypes>=1.0.20.13
Requires-Dist: ipython>=8.26.0
Requires-Dist: ipykernel>=6.29.5
Requires-Dist: matplotlib>=3.9.2
Requires-Dist: mplfinance>=0.12.10b0
Requires-Dist: nest_asyncio>=1.6.0
Requires-Dist: numpy>=2.1.0
Requires-Dist: pandas>=2.2.2
Requires-Dist: pandas-stubs>=2.2.2
Requires-Dist: psycopg[binary]>=3.1.19
Requires-Dist: pytest>=8.3.2
Requires-Dist: python-dotenv>=1.0.1
Requires-Dist: requests>=2.32.3
Requires-Dist: rollbar>=1.0.0
Requires-Dist: setuptools>=73.0.1
Requires-Dist: sqlalchemy>=2.0.32
Requires-Dist: sqlalchemy-utils>=0.41.2
Requires-Dist: streamlit>=1.37.1
Requires-Dist: tabulate>=0.9.0
Requires-Dist: tqdm>=4.66.5
Requires-Dist: web3>=7.6.0
Requires-Dist: agent0[dev, rollbar] ; extra == "all"
Requires-Dist: autodocsumm>=0.2.11 ; extra == "dev"
Requires-Dist: black==24.* ; extra == "dev"
Requires-Dist: coverage ; extra == "dev"
Requires-Dist: ipykernel ; extra == "dev"
Requires-Dist: jupytext ; extra == "dev"
Requires-Dist: myst-parser>=2.0.0 ; extra == "dev"
Requires-Dist: nbconvert ; extra == "dev"
Requires-Dist: nbsphinx>=0.8.12 ; extra == "dev"
Requires-Dist: numpydoc>=1.5.0 ; extra == "dev"
Requires-Dist: pylint>=3.3.0 ; extra == "dev"
Requires-Dist: pytest-postgresql ; extra == "dev"
Requires-Dist: pyright ; extra == "dev"
Requires-Dist: sphinx>=6 ; extra == "dev"
Requires-Dist: sphinx-autoapi>=2.0.1 ; extra == "dev"
Requires-Dist: sphinx_autodoc_typehints>=1.21.8 ; extra == "dev"
Requires-Dist: sphinx-rtd-theme>=1.2.2 ; extra == "dev"
Requires-Dist: sphinxcontrib-napoleon>=0.7 ; extra == "dev"
Requires-Dist: tomli>=2.0.1 ; extra == "dev"
Requires-Dist: urllib3 ; extra == "dev"
Requires-Dist: rollbar ; extra == "rollbar"
Project-URL: Bug Tracker, https://github.com/delvtech/agent0/issues
Project-URL: Homepage, https://agent0.readthedocs.io/en/latest/
Provides-Extra: all
Provides-Extra: dev
Provides-Extra: rollbar
